dicognito/__init__.py
dicognito/__main__.py
dicognito/_config.py
dicognito/_version.py
dicognito/addressanonymizer.py
dicognito/anonymizer.py
dicognito/dataset_updater.py
dicognito/datetimeanonymizer.py
dicognito/element_anonymizer.py
dicognito/equipmentanonymizer.py
dicognito/exceptions.py
dicognito/filters.py
dicognito/fixedvalueanonymizer.py
dicognito/idanonymizer.py
dicognito/pipeline.py
dicognito/pnanonymizer.py
dicognito/py.typed
dicognito/randomizer.py
dicognito/release_notes.md
dicognito/uianonymizer.py
dicognito/unwantedelements.py
dicognito/value_keeper.py
dicognito-0.19.0.dist-info/METADATA
dicognito-0.19.0.dist-info/WHEEL
dicognito-0.19.0.dist-info/entry_points.txt
dicognito-0.19.0.dist-info/licenses/LICENSE
dicognito-0.19.0.dist-info/RECORD
