Metadata-Version: 2.4
Name: dicognito
Version: 0.19.0
Summary: A tool for anonymizing DICOM files
Project-URL: Changelog, https://github.com/blairconrad/dicognito/blob/main/src/dicognito/release_notes.md
Project-URL: Documentation, https://github.com/blairconrad/dicognito/blob/main/README.md
Project-URL: Homepage, https://github.com/blairconrad/dicognito
Project-URL: Issues, https://github.com/blairconrad/dicognito/issues
Project-URL: Repository, https://github.com/blairconrad/dicognito
Author-email: Blair Conrad <blair@blairconrad.com>
License-File: LICENSE
Keywords: anonymize,deidentify,dicom
Classifier: Development Status :: 3 - Alpha
Classifier: Environment :: Console
Classifier: Intended Audience :: Healthcare Industry
Classifier: License :: OSI Approved :: MIT License
Classifier: Operating System :: OS Independent
Classifier: Programming Language :: Python :: 3
Classifier: Programming Language :: Python :: 3.10
Classifier: Programming Language :: Python :: 3.11
Classifier: Programming Language :: Python :: 3.12
Classifier: Programming Language :: Python :: 3.13
Classifier: Programming Language :: Python :: 3.14
Classifier: Topic :: Scientific/Engineering :: Medical Science Apps.
Classifier: Topic :: Software Development :: Libraries
Classifier: Typing :: Typed
Requires-Python: >=3.10
Requires-Dist: pydicom>=3.0.1
